odoo/addons/l10n_it_delivery_note_batch/README.rst
odoo/addons/l10n_it_delivery_note_batch/__init__.py
odoo/addons/l10n_it_delivery_note_batch/__manifest__.py
odoo/addons/l10n_it_delivery_note_batch/i18n/it.po
odoo/addons/l10n_it_delivery_note_batch/i18n/l10n_it_delivery_note_batch.pot
odoo/addons/l10n_it_delivery_note_batch/models/__init__.py
odoo/addons/l10n_it_delivery_note_batch/models/stock_delivery_note.py
odoo/addons/l10n_it_delivery_note_batch/models/stock_picking_batch.py
odoo/addons/l10n_it_delivery_note_batch/readme/CONTRIBUTORS.md
odoo/addons/l10n_it_delivery_note_batch/readme/DESCRIPTION.md
odoo/addons/l10n_it_delivery_note_batch/readme/USAGE.md
odoo/addons/l10n_it_delivery_note_batch/static/description/icon.png
odoo/addons/l10n_it_delivery_note_batch/static/description/index.html
odoo/addons/l10n_it_delivery_note_batch/views/stock_picking_batch_views.xml
odoo/addons/l10n_it_delivery_note_batch/views/stock_picking_views.xml
odoo_addon_l10n_it_delivery_note_batch-18.0.1.0.0.2.dist-info/METADATA
odoo_addon_l10n_it_delivery_note_batch-18.0.1.0.0.2.dist-info/WHEEL
odoo_addon_l10n_it_delivery_note_batch-18.0.1.0.0.2.dist-info/top_level.txt
odoo_addon_l10n_it_delivery_note_batch-18.0.1.0.0.2.dist-info/RECORD
