Metadata-Version: 2.1
Name: odoo-addon-l10n_it_delivery_note_batch
Version: 18.0.1.0.0.2
Requires-Python: >=3.10
Requires-Dist: odoo-addon-l10n_it_delivery_note==18.0.*
Requires-Dist: odoo==18.0.*
Summary: Crea i DDT partendo da gruppi di prelievi
Home-page: https://github.com/OCA/l10n-italy
License: AGPL-3
Author: Marco Colombo, Odoo Community Association (OCA)
Author-email: support@odoo-community.org
Classifier: Programming Language :: Python
Classifier: Framework :: Odoo
Classifier: Framework :: Odoo :: 18.0
Classifier: License :: OSI Approved :: GNU Affero General Public License v3
